pyclean/__init__.py
pyclean/__main__.py
pyclean/cli.py
pyclean/entries.py
pyclean/meta.py
pyclean.py-0.0.1.dist-info/LICENSE
pyclean.py-0.0.1.dist-info/METADATA
pyclean.py-0.0.1.dist-info/WHEEL
pyclean.py-0.0.1.dist-info/entry_points.txt
pyclean.py-0.0.1.dist-info/top_level.txt
pyclean.py-0.0.1.dist-info/zip-safe
pyclean.py-0.0.1.dist-info/RECORD
