Metadata-Version: 2.1
Name: pyclean.py
Version: 0.0.1
Summary: Clean compiled from a Python project.
Home-page: https://github.com/uranusjr/pyclean-py
Author: Tzu-ping Chung
Author-email: uranusjr@gmail.com
License: ISC License
Platform: UNKNOWN
Classifier: Development Status :: 3 - Alpha
Classifier: License :: OSI Approved :: ISC License (ISCL)
Classifier: Operating System :: OS Independent
Classifier: Programming Language :: Python :: 2
Classifier: Programming Language :: Python :: 2.7
Classifier: Programming Language :: Python :: 3
Classifier: Programming Language :: Python :: 3.4
Classifier: Programming Language :: Python :: 3.5
Classifier: Programming Language :: Python :: 3.6
Classifier: Programming Language :: Python :: 3.7
Classifier: Topic :: Software Development :: Libraries :: Python Modules
Requires-Python: >=2.7,!=3.0,!=3.1,!=3.2,!=3.3
